RecordsKeeperPython3Lib/__init__.py
RecordsKeeperPython3Lib/address.py
RecordsKeeperPython3Lib/assets.py
RecordsKeeperPython3Lib/block.py
RecordsKeeperPython3Lib/blockchain.py
RecordsKeeperPython3Lib/permissions.py
RecordsKeeperPython3Lib/stream.py
RecordsKeeperPython3Lib/transaction.py
RecordsKeeperPython3Lib/wallet.py
RecordsKeeperPython3Lib/test/__init__.py
RecordsKeeperPython3Lib/test/test_address.py
RecordsKeeperPython3Lib/test/test_assets.py
RecordsKeeperPython3Lib/test/test_block.py
RecordsKeeperPython3Lib/test/test_blockchain.py
RecordsKeeperPython3Lib/test/test_permissions.py
RecordsKeeperPython3Lib/test/test_stream.py
RecordsKeeperPython3Lib/test/test_transaction.py
RecordsKeeperPython3Lib/test/test_wallet.py
RecordsKeeperPython3Lib-0.1.1.dist-info/DESCRIPTION.rst
RecordsKeeperPython3Lib-0.1.1.dist-info/METADATA
RecordsKeeperPython3Lib-0.1.1.dist-info/RECORD
RecordsKeeperPython3Lib-0.1.1.dist-info/WHEEL
RecordsKeeperPython3Lib-0.1.1.dist-info/metadata.json
RecordsKeeperPython3Lib-0.1.1.dist-info/top_level.txt
